Metadata-Version: 1.2
Name: conversion-onnx
Version: 0.0.4
Summary: library 
Home-page: UNKNOWN
Author: wangyp
Author-email: 562584614@qq.com
License: MIT Licence
Keywords: pytorch onnx util
Platform: any
Requires-Python: >=3.6.*
